README.md
setup.py
pynet/__init__.py
pynet/icmp.py
pynet/version.py
pynet.egg-info/PKG-INFO
pynet.egg-info/SOURCES.txt
pynet.egg-info/dependency_links.txt
pynet.egg-info/not-zip-safe
pynet.egg-info/top_level.txt